MANIFEST.in
README.rst
setup.py
docs/HISTORY.txt
docs/LICENSE.GPL
docs/LICENSE.txt
ftw/__init__.py
ftw.iframeblock.egg-info/PKG-INFO
ftw.iframeblock.egg-info/SOURCES.txt
ftw.iframeblock.egg-info/dependency_links.txt
ftw.iframeblock.egg-info/entry_points.txt
ftw.iframeblock.egg-info/namespace_packages.txt
ftw.iframeblock.egg-info/not-zip-safe
ftw.iframeblock.egg-info/requires.txt
ftw.iframeblock.egg-info/top_level.txt
ftw/iframeblock/__init__.py
ftw/iframeblock/configure.zcml
ftw/iframeblock/lawgiver.zcml
ftw/iframeblock/permissions.zcml
ftw/iframeblock/resources.zcml
ftw/iframeblock/testing.py
ftw/iframeblock/browser/__init__.py
ftw/iframeblock/browser/configure.zcml
ftw/iframeblock/browser/iframeblock.py
ftw/iframeblock/browser/resources/iframeResizer.contentWindow.js
ftw/iframeblock/browser/resources/iframeResizer.contentWindow.map
ftw/iframeblock/browser/resources/iframeResizer.contentWindow.min.js
ftw/iframeblock/browser/resources/iframeResizer.js
ftw/iframeblock/browser/resources/iframeResizer.map
ftw/iframeblock/browser/resources/iframeResizer.min.js
ftw/iframeblock/browser/resources/iframeblock-compiled.js
ftw/iframeblock/browser/resources/iframeblock.js
ftw/iframeblock/browser/resources/main.js
ftw/iframeblock/browser/resources/styles.scss
ftw/iframeblock/browser/templates/iframeblock.pt
ftw/iframeblock/contents/__init__.py
ftw/iframeblock/contents/iframeblock.py
ftw/iframeblock/contents/interfaces.py
ftw/iframeblock/locales/ftw.iframeblock.pot
ftw/iframeblock/locales/ftw.lawgiver.pot
ftw/iframeblock/locales/plone.pot
ftw/iframeblock/locales/de/LC_MESSAGES/ftw.iframeblock.po
ftw/iframeblock/locales/de/LC_MESSAGES/ftw.lawgiver.po
ftw/iframeblock/locales/de/LC_MESSAGES/plone.po
ftw/iframeblock/locales/en/LC_MESSAGES/ftw.iframeblock.po
ftw/iframeblock/locales/en/LC_MESSAGES/ftw.lawgiver.po
ftw/iframeblock/locales/en/LC_MESSAGES/plone.po
ftw/iframeblock/profiles/default/jsregistry.xml
ftw/iframeblock/profiles/default/metadata.xml
ftw/iframeblock/profiles/default/propertiestool.xml
ftw/iframeblock/profiles/default/rolemap.xml
ftw/iframeblock/profiles/default/types.xml
ftw/iframeblock/profiles/default/workflows.xml
ftw/iframeblock/profiles/default/types/Plone_Site.xml
ftw/iframeblock/profiles/default/types/ftw.iframeblock.IFrameBlock.xml
